univer_db/__init__.py
univer_db/config.py
univer_db/orm.py
univer_db/models/__init__.py
univer_db/models/base.py
univer_db/models/dormitories.py
univer_db/models/grades.py
univer_db/models/groups.py
univer_db/models/models.py
univer_db/models/orders.py
univer_db/models/roles.py
univer_db/models/sheets.py
univer_db/models/structures.py
python_univer-0.5.4.dist-info/LICENSE
python_univer-0.5.4.dist-info/METADATA
python_univer-0.5.4.dist-info/WHEEL
python_univer-0.5.4.dist-info/top_level.txt
python_univer-0.5.4.dist-info/RECORD
