Metadata-Version: 2.1
Name: python-univer
Version: 0.5.4
Summary: Данная библиотека содержить SqlAlchemy ORM для системы Univer
Home-page: https://github.com/yessenovuniversity/python_univer
Author: Nauryzbek Aitbayev
Author-email: nauryzbek.aitbayev@yu.edu.kz
License: UNKNOWN
Platform: UNKNOWN
Classifier: Programming Language :: Python :: 3
Classifier: License :: Other/Proprietary License
Classifier: Operating System :: OS Independent
Requires-Python: >=3.6
License-File: LICENSE
Requires-Dist: sqlalchemy
Requires-Dist: pyodbc
